medDataSdk/__init__.py
medDataSdk/meddatasdk.py
meddatasdk-1.0.0.dist-info/METADATA
meddatasdk-1.0.0.dist-info/WHEEL
meddatasdk-1.0.0.dist-info/top_level.txt
meddatasdk-1.0.0.dist-info/RECORD
